geo_auth/Serializer.py
geo_auth/__init__.py
geo_auth/admin.py
geo_auth/apps.py
geo_auth/database.py
geo_auth/middleware.py
geo_auth/models.py
geo_auth/task.py
geo_auth/tests.py
geo_auth/urls.py
geo_auth/utility.py
geo_auth/views.py
geo_auth/iplite_database/IP2LOCATION-LITE-ASN.BIN
geo_auth/iplite_database/IP2LOCATION-LITE-DB11.BIN
geo_auth/iplite_database/LICENSE_LITE.TXT
geo_auth/iplite_database/README_LITE.TXT
geo_auth/migrations/__init__.py
geo_auth-1.1.0.dist-info/licenses/LICENSE
geo_auth-1.1.0.dist-info/METADATA
geo_auth-1.1.0.dist-info/WHEEL
geo_auth-1.1.0.dist-info/top_level.txt
geo_auth-1.1.0.dist-info/RECORD
