Metadata-Version: 2.4
Name: geo_auth
Version: 1.1.0
Summary: Django plugin for geolocation info
Author-email: Shoile Abdulazeez Adenuga <shoabdulazeez@gmail.com>
License-Expression: MIT
Project-URL: Homepage, https://github.com/shoileazeez/drf_geodata.git
Project-URL: Issues, https://github.com/shoileazeez/drf_geodata/issues
Keywords: Django,geolocation,plugin,authentication
Classifier: Framework :: Django
Classifier: Programming Language :: Python :: 3
Classifier: Operating System :: OS Independent
Requires-Python: >=3.12
License-File: LICENSE
Requires-Dist: APScheduler==3.11.0
Requires-Dist: Django==5.1.6
Requires-Dist: django-ipware==4.0.2
Requires-Dist: djangorestframework==3.15.2
Requires-Dist: IP2Location==8.10.5
Requires-Dist: requests==2.32.3
Requires-Dist: pycountry==24.6.1
Requires-Dist: python-dotenv==1.0.0
Requires-Dist: tzlocal==5.3.1
Requires-Dist: timezonefinder==6.5.8
Requires-Dist: user-agents==2.2.0
Requires-Dist: iso3166==2.1.1
Dynamic: license-file
